{
    "pais": "España",
    "copa": "Supercopa (España)",
    "año_inicio": 1997,
    "temporada": "1997-98",
    "cuadro_honor": {
        "campeon": "Real Madrid",
        "subcampeon": "Barcelona"
    },
    "partidos": [
        {
            "id_partido": 490110,
            "ronda": "Final - Ida",
            "local": "Barcelona",
            "visitante": "Real Madrid",
            "goles_local": "2",
            "goles_visitante": "1",
            "hubo_penaltis": false,
            "penaltis_local": null,
            "penaltis_visitante": null
        },
        {
            "id_partido": 490111,
            "ronda": "Final - Vuelta",
            "local": "Real Madrid",
            "visitante": "Barcelona",
            "goles_local": "4",
            "goles_visitante": "1",
            "hubo_penaltis": false,
            "penaltis_local": null,
            "penaltis_visitante": null
        }
    ]
}