{
    "pais": "España",
    "equipo": "Real Sociedad",
    "id_bdfutbol": "30",
    "temporada": "1950-51",
    "año_inicio": 1950,
    "competiciones": {
        "Liga Regular": [
            {
                "id": "j8415",
                "nombre": "Eizaguirre",
                "posicion": "portero",
                "partidos_jugados": 30,
                "partidos_titular": 30,
                "minutos": 2700,
                "goles_marcados": 0,
                "goles_encajados": 56
            },
            {
                "id": "j10152",
                "nombre": "Marculeta II",
                "posicion": "defensa",
                "partidos_jugados": 30,
                "partidos_titular": 30,
                "minutos": 2700,
                "goles_marcados": 0,
                "goles_encajados": 0
            },
            {
                "id": "j9645",
                "nombre": "Suárez",
                "posicion": "defensa",
                "partidos_jugados": 30,
                "partidos_titular": 30,
                "minutos": 2700,
                "goles_marcados": 0,
                "goles_encajados": 0
            },
            {
                "id": "j10151",
                "nombre": "Murillo",
                "posicion": "defensa",
                "partidos_jugados": 24,
                "partidos_titular": 24,
                "minutos": 2160,
                "goles_marcados": 1,
                "goles_encajados": 0
            },
            {
                "id": "j9975",
                "nombre": "Ontoria",
                "posicion": "centrocampista",
                "partidos_jugados": 29,
                "partidos_titular": 29,
                "minutos": 2610,
                "goles_marcados": 6,
                "goles_encajados": 0
            },
            {
                "id": "j7430",
                "nombre": "Artigas",
                "posicion": "centrocampista",
                "partidos_jugados": 27,
                "partidos_titular": 27,
                "minutos": 2430,
                "goles_marcados": 0,
                "goles_encajados": 0
            },
            {
                "id": "j9971",
                "nombre": "Epi",
                "posicion": "extremo",
                "partidos_jugados": 30,
                "partidos_titular": 30,
                "minutos": 2700,
                "goles_marcados": 17,
                "goles_encajados": 0
            },
            {
                "id": "j9891",
                "nombre": "Igoa",
                "posicion": "extremo",
                "partidos_jugados": 30,
                "partidos_titular": 30,
                "minutos": 2700,
                "goles_marcados": 11,
                "goles_encajados": 0
            },
            {
                "id": "j10242",
                "nombre": "Caeiro",
                "posicion": "extremo",
                "partidos_jugados": 24,
                "partidos_titular": 24,
                "minutos": 2160,
                "goles_marcados": 17,
                "goles_encajados": 0
            },
            {
                "id": "j7531",
                "nombre": "Barinaga",
                "posicion": "delantero centro",
                "partidos_jugados": 23,
                "partidos_titular": 23,
                "minutos": 2070,
                "goles_marcados": 10,
                "goles_encajados": 0
            },
            {
                "id": "j9976",
                "nombre": "Pérez",
                "posicion": "extremo",
                "partidos_jugados": 23,
                "partidos_titular": 23,
                "minutos": 2061,
                "goles_marcados": 6,
                "goles_encajados": 0
            },
            {
                "id": "j10049",
                "nombre": "Castivia",
                "posicion": "extremo",
                "partidos_jugados": 11,
                "partidos_titular": 11,
                "minutos": 990,
                "goles_marcados": 4,
                "goles_encajados": 0
            },
            {
                "id": "j10047",
                "nombre": "Basabe",
                "posicion": "extremo",
                "partidos_jugados": 5,
                "partidos_titular": 5,
                "minutos": 450,
                "goles_marcados": 2,
                "goles_encajados": 0
            },
            {
                "id": "j10075",
                "nombre": "Bernal",
                "posicion": "defensa",
                "partidos_jugados": 4,
                "partidos_titular": 4,
                "minutos": 360,
                "goles_marcados": 0,
                "goles_encajados": 0
            },
            {
                "id": "j8162",
                "nombre": "Peporro",
                "posicion": "centrocampista",
                "partidos_jugados": 3,
                "partidos_titular": 3,
                "minutos": 270,
                "goles_marcados": 0,
                "goles_encajados": 0
            },
            {
                "id": "j10220",
                "nombre": "Patri",
                "posicion": "defensa",
                "partidos_jugados": 2,
                "partidos_titular": 2,
                "minutos": 180,
                "goles_marcados": 0,
                "goles_encajados": 0
            },
            {
                "id": "j10149",
                "nombre": "Aldonza",
                "posicion": "defensa",
                "partidos_jugados": 2,
                "partidos_titular": 2,
                "minutos": 180,
                "goles_marcados": 0,
                "goles_encajados": 0
            },
            {
                "id": "j8285",
                "nombre": "Paz",
                "posicion": "extremo",
                "partidos_jugados": 2,
                "partidos_titular": 2,
                "minutos": 180,
                "goles_marcados": 1,
                "goles_encajados": 0
            },
            {
                "id": "j10013",
                "nombre": "Hériz",
                "posicion": "extremo",
                "partidos_jugados": 1,
                "partidos_titular": 1,
                "minutos": 90,
                "goles_marcados": 0,
                "goles_encajados": 0
            }
        ],
        "Copa del Rey (España)": [
            {
                "id": "j8415",
                "nombre": "Eizaguirre",
                "posicion": "portero",
                "partidos_jugados": 6,
                "partidos_titular": 6,
                "minutos": 505,
                "goles_marcados": 0,
                "goles_encajados": 5
            },
            {
                "id": "j10152",
                "nombre": "Marculeta II",
                "posicion": "defensa",
                "partidos_jugados": 5,
                "partidos_titular": 5,
                "minutos": 450,
                "goles_marcados": 0,
                "goles_encajados": 0
            },
            {
                "id": "j9645",
                "nombre": "Suárez",
                "posicion": "defensa",
                "partidos_jugados": 7,
                "partidos_titular": 7,
                "minutos": 630,
                "goles_marcados": 0,
                "goles_encajados": 0
            },
            {
                "id": "j10151",
                "nombre": "Murillo",
                "posicion": "defensa",
                "partidos_jugados": 6,
                "partidos_titular": 6,
                "minutos": 540,
                "goles_marcados": 0,
                "goles_encajados": 0
            },
            {
                "id": "j9975",
                "nombre": "Ontoria",
                "posicion": "centrocampista",
                "partidos_jugados": 6,
                "partidos_titular": 6,
                "minutos": 540,
                "goles_marcados": 2,
                "goles_encajados": 0
            },
            {
                "id": "j7430",
                "nombre": "Artigas",
                "posicion": "centrocampista",
                "partidos_jugados": 4,
                "partidos_titular": 4,
                "minutos": 360,
                "goles_marcados": 1,
                "goles_encajados": 0
            },
            {
                "id": "j9971",
                "nombre": "Epi",
                "posicion": "extremo",
                "partidos_jugados": 6,
                "partidos_titular": 6,
                "minutos": 540,
                "goles_marcados": 0,
                "goles_encajados": 0
            },
            {
                "id": "j9891",
                "nombre": "Igoa",
                "posicion": "extremo",
                "partidos_jugados": 3,
                "partidos_titular": 3,
                "minutos": 270,
                "goles_marcados": 1,
                "goles_encajados": 0
            },
            {
                "id": "j10242",
                "nombre": "Caeiro",
                "posicion": "extremo",
                "partidos_jugados": 6,
                "partidos_titular": 6,
                "minutos": 540,
                "goles_marcados": 2,
                "goles_encajados": 0
            },
            {
                "id": "j7531",
                "nombre": "Barinaga",
                "posicion": "delantero centro",
                "partidos_jugados": 5,
                "partidos_titular": 5,
                "minutos": 450,
                "goles_marcados": 4,
                "goles_encajados": 0
            },
            {
                "id": "j9976",
                "nombre": "Pérez",
                "posicion": "extremo",
                "partidos_jugados": 7,
                "partidos_titular": 7,
                "minutos": 630,
                "goles_marcados": 1,
                "goles_encajados": 0
            },
            {
                "id": "j8196",
                "nombre": "Bagur",
                "posicion": "portero",
                "partidos_jugados": 2,
                "partidos_titular": 1,
                "minutos": 125,
                "goles_marcados": 0,
                "goles_encajados": 2
            },
            {
                "id": "j10049",
                "nombre": "Castivia",
                "posicion": "extremo",
                "partidos_jugados": 1,
                "partidos_titular": 1,
                "minutos": 90,
                "goles_marcados": 0,
                "goles_encajados": 0
            },
            {
                "id": "j10075",
                "nombre": "Bernal",
                "posicion": "defensa",
                "partidos_jugados": 3,
                "partidos_titular": 3,
                "minutos": 270,
                "goles_marcados": 0,
                "goles_encajados": 0
            },
            {
                "id": "j10220",
                "nombre": "Patri",
                "posicion": "defensa",
                "partidos_jugados": 4,
                "partidos_titular": 4,
                "minutos": 360,
                "goles_marcados": 0,
                "goles_encajados": 0
            },
            {
                "id": "j9777",
                "nombre": "Alsúa II",
                "posicion": "centrocampista",
                "partidos_jugados": 7,
                "partidos_titular": 7,
                "minutos": 630,
                "goles_marcados": 3,
                "goles_encajados": 0
            }
        ]
    }
}