{
    "pais": "España",
    "equipo": "Levante",
    "id_bdfutbol": "20",
    "temporada": "1988-89",
    "año_inicio": 1988,
    "competiciones": {
        "Liga Regular": [
            {
                "id": "j9256",
                "nombre": "Museros",
                "posicion": "portero",
                "partidos_jugados": 37,
                "partidos_titular": 37,
                "minutos": 3330,
                "goles_marcados": 0,
                "goles_encajados": 27
            },
            {
                "id": "j9247",
                "nombre": "Ballester",
                "posicion": "defensa",
                "partidos_jugados": 38,
                "partidos_titular": 38,
                "minutos": 3420,
                "goles_marcados": 0,
                "goles_encajados": 0
            },
            {
                "id": "j9252",
                "nombre": "Iranzo",
                "posicion": "defensa",
                "partidos_jugados": 23,
                "partidos_titular": 22,
                "minutos": 1746,
                "goles_marcados": 1,
                "goles_encajados": 0
            },
            {
                "id": "j3221",
                "nombre": "Blesa",
                "posicion": "central",
                "partidos_jugados": 22,
                "partidos_titular": 22,
                "minutos": 1935,
                "goles_marcados": 2,
                "goles_encajados": 0
            },
            {
                "id": "j9246",
                "nombre": "Aragó",
                "posicion": "defensa",
                "partidos_jugados": 25,
                "partidos_titular": 21,
                "minutos": 2052,
                "goles_marcados": 3,
                "goles_encajados": 0
            },
            {
                "id": "j3827",
                "nombre": "Susaeta",
                "posicion": "centrocampista",
                "partidos_jugados": 37,
                "partidos_titular": 37,
                "minutos": 3330,
                "goles_marcados": 4,
                "goles_encajados": 0
            },
            {
                "id": "j11915",
                "nombre": "Latorre",
                "posicion": "centrocampista",
                "partidos_jugados": 36,
                "partidos_titular": 35,
                "minutos": 3120,
                "goles_marcados": 15,
                "goles_encajados": 0
            },
            {
                "id": "j302763",
                "nombre": "Patri",
                "posicion": "centrocampista",
                "partidos_jugados": 35,
                "partidos_titular": 35,
                "minutos": 3030,
                "goles_marcados": 1,
                "goles_encajados": 0
            },
            {
                "id": "j3202",
                "nombre": "López",
                "posicion": "centrocampista",
                "partidos_jugados": 32,
                "partidos_titular": 29,
                "minutos": 2387,
                "goles_marcados": 17,
                "goles_encajados": 0
            },
            {
                "id": "j3596",
                "nombre": "Martín Pérez",
                "posicion": "extremo",
                "partidos_jugados": 35,
                "partidos_titular": 30,
                "minutos": 2423,
                "goles_marcados": 7,
                "goles_encajados": 0
            },
            {
                "id": "j12740",
                "nombre": "López Ufarte",
                "posicion": "extremo",
                "partidos_jugados": 20,
                "partidos_titular": 18,
                "minutos": 1507,
                "goles_marcados": 1,
                "goles_encajados": 0
            },
            {
                "id": "j403652",
                "nombre": "Moreno",
                "posicion": "portero",
                "partidos_jugados": 1,
                "partidos_titular": 1,
                "minutos": 90,
                "goles_marcados": 0,
                "goles_encajados": 2
            },
            {
                "id": "j1818",
                "nombre": "Verde",
                "posicion": "centrocampista",
                "partidos_jugados": 26,
                "partidos_titular": 17,
                "minutos": 1700,
                "goles_marcados": 3,
                "goles_encajados": 0
            },
            {
                "id": "j2210",
                "nombre": "Corbalán",
                "posicion": "extremo",
                "partidos_jugados": 30,
                "partidos_titular": 13,
                "minutos": 1394,
                "goles_marcados": 8,
                "goles_encajados": 0
            },
            {
                "id": "j3174",
                "nombre": "Abad",
                "posicion": "centrocampista",
                "partidos_jugados": 22,
                "partidos_titular": 21,
                "minutos": 1924,
                "goles_marcados": 1,
                "goles_encajados": 0
            },
            {
                "id": "j3318",
                "nombre": "Rastrojo",
                "posicion": "lateral izquierdo",
                "partidos_jugados": 18,
                "partidos_titular": 17,
                "minutos": 1387,
                "goles_marcados": 0,
                "goles_encajados": 0
            },
            {
                "id": "j7160",
                "nombre": "Almagro",
                "posicion": "defensa",
                "partidos_jugados": 16,
                "partidos_titular": 11,
                "minutos": 1076,
                "goles_marcados": 0,
                "goles_encajados": 0
            },
            {
                "id": "j402675",
                "nombre": "Llario",
                "posicion": "extremo",
                "partidos_jugados": 12,
                "partidos_titular": 3,
                "minutos": 463,
                "goles_marcados": 1,
                "goles_encajados": 0
            },
            {
                "id": "j11914",
                "nombre": "Porras",
                "posicion": "centrocampista",
                "partidos_jugados": 9,
                "partidos_titular": 5,
                "minutos": 489,
                "goles_marcados": 0,
                "goles_encajados": 0
            },
            {
                "id": "j403651",
                "nombre": "Gigi",
                "posicion": "centrocampista",
                "partidos_jugados": 7,
                "partidos_titular": 4,
                "minutos": 369,
                "goles_marcados": 0,
                "goles_encajados": 0
            },
            {
                "id": "j9253",
                "nombre": "Mascarell",
                "posicion": "defensa",
                "partidos_jugados": 5,
                "partidos_titular": 1,
                "minutos": 123,
                "goles_marcados": 0,
                "goles_encajados": 0
            },
            {
                "id": "j7035",
                "nombre": "Olivas",
                "posicion": "extremo",
                "partidos_jugados": 2,
                "partidos_titular": 1,
                "minutos": 85,
                "goles_marcados": 0,
                "goles_encajados": 0
            }
        ],
        "Copa del Rey (España)": [
            {
                "id": "j9256",
                "nombre": "Museros",
                "posicion": "portero",
                "partidos_jugados": 4,
                "partidos_titular": 4,
                "minutos": 390,
                "goles_marcados": 0,
                "goles_encajados": 8
            },
            {
                "id": "j9247",
                "nombre": "Ballester",
                "posicion": "defensa",
                "partidos_jugados": 4,
                "partidos_titular": 4,
                "minutos": 345,
                "goles_marcados": 0,
                "goles_encajados": 0
            },
            {
                "id": "j9252",
                "nombre": "Iranzo",
                "posicion": "defensa",
                "partidos_jugados": 3,
                "partidos_titular": 3,
                "minutos": 300,
                "goles_marcados": 0,
                "goles_encajados": 0
            },
            {
                "id": "j9246",
                "nombre": "Aragó",
                "posicion": "defensa",
                "partidos_jugados": 2,
                "partidos_titular": 2,
                "minutos": 210,
                "goles_marcados": 0,
                "goles_encajados": 0
            },
            {
                "id": "j3827",
                "nombre": "Susaeta",
                "posicion": "centrocampista",
                "partidos_jugados": 4,
                "partidos_titular": 4,
                "minutos": 390,
                "goles_marcados": 2,
                "goles_encajados": 0
            },
            {
                "id": "j11915",
                "nombre": "Latorre",
                "posicion": "centrocampista",
                "partidos_jugados": 4,
                "partidos_titular": 4,
                "minutos": 367,
                "goles_marcados": 1,
                "goles_encajados": 0
            },
            {
                "id": "j302763",
                "nombre": "Patri",
                "posicion": "centrocampista",
                "partidos_jugados": 4,
                "partidos_titular": 4,
                "minutos": 390,
                "goles_marcados": 0,
                "goles_encajados": 0
            },
            {
                "id": "j3202",
                "nombre": "López",
                "posicion": "centrocampista",
                "partidos_jugados": 3,
                "partidos_titular": 0,
                "minutos": 90,
                "goles_marcados": 0,
                "goles_encajados": 0
            },
            {
                "id": "j3596",
                "nombre": "Martín Pérez",
                "posicion": "extremo",
                "partidos_jugados": 4,
                "partidos_titular": 4,
                "minutos": 320,
                "goles_marcados": 1,
                "goles_encajados": 0
            },
            {
                "id": "j12740",
                "nombre": "López Ufarte",
                "posicion": "extremo",
                "partidos_jugados": 4,
                "partidos_titular": 4,
                "minutos": 368,
                "goles_marcados": 0,
                "goles_encajados": 0
            },
            {
                "id": "j1818",
                "nombre": "Verde",
                "posicion": "centrocampista",
                "partidos_jugados": 3,
                "partidos_titular": 2,
                "minutos": 199,
                "goles_marcados": 0,
                "goles_encajados": 0
            },
            {
                "id": "j2210",
                "nombre": "Corbalán",
                "posicion": "extremo",
                "partidos_jugados": 4,
                "partidos_titular": 3,
                "minutos": 248,
                "goles_marcados": 2,
                "goles_encajados": 0
            },
            {
                "id": "j3318",
                "nombre": "Rastrojo",
                "posicion": "lateral izquierdo",
                "partidos_jugados": 2,
                "partidos_titular": 2,
                "minutos": 180,
                "goles_marcados": 0,
                "goles_encajados": 0
            },
            {
                "id": "j11914",
                "nombre": "Porras",
                "posicion": "centrocampista",
                "partidos_jugados": 2,
                "partidos_titular": 2,
                "minutos": 180,
                "goles_marcados": 0,
                "goles_encajados": 0
            },
            {
                "id": "j403651",
                "nombre": "Gigi",
                "posicion": "centrocampista",
                "partidos_jugados": 4,
                "partidos_titular": 2,
                "minutos": 277,
                "goles_marcados": 0,
                "goles_encajados": 0
            },
            {
                "id": "j9253",
                "nombre": "Mascarell",
                "posicion": "defensa",
                "partidos_jugados": 1,
                "partidos_titular": 0,
                "minutos": 36,
                "goles_marcados": 0,
                "goles_encajados": 0
            }
        ]
    }
}