{
    "pais": "España",
    "equipo": "Alaves",
    "id_bdfutbol": "3",
    "temporada": "2021-22",
    "año_inicio": 2021,
    "competiciones": {
        "Liga Regular": [
            {
                "id": "j7502",
                "nombre": "Pacheco",
                "posicion": "portero",
                "partidos_jugados": 34,
                "partidos_titular": 34,
                "minutos": 3054,
                "goles_marcados": 0,
                "goles_encajados": 60
            },
            {
                "id": "j28148",
                "nombre": "Aguirregabiria",
                "posicion": "lateral derecho",
                "partidos_jugados": 24,
                "partidos_titular": 17,
                "minutos": 1616,
                "goles_marcados": 0,
                "goles_encajados": 0
            },
            {
                "id": "j301809",
                "nombre": "Duarte",
                "posicion": "lateral izquierdo",
                "partidos_jugados": 34,
                "partidos_titular": 31,
                "minutos": 2629,
                "goles_marcados": 0,
                "goles_encajados": 0
            },
            {
                "id": "j12435",
                "nombre": "Laguardia",
                "posicion": "central",
                "partidos_jugados": 34,
                "partidos_titular": 34,
                "minutos": 3044,
                "goles_marcados": 3,
                "goles_encajados": 0
            },
            {
                "id": "j13748",
                "nombre": "Lejeune",
                "posicion": "central",
                "partidos_jugados": 30,
                "partidos_titular": 30,
                "minutos": 2700,
                "goles_marcados": 0,
                "goles_encajados": 0
            },
            {
                "id": "j29027",
                "nombre": "Loum",
                "posicion": "centrocampista",
                "partidos_jugados": 32,
                "partidos_titular": 26,
                "minutos": 2316,
                "goles_marcados": 2,
                "goles_encajados": 0
            },
            {
                "id": "j28156",
                "nombre": "Toni Moya",
                "posicion": "centrocampista",
                "partidos_jugados": 28,
                "partidos_titular": 17,
                "minutos": 1387,
                "goles_marcados": 0,
                "goles_encajados": 0
            },
            {
                "id": "j16310",
                "nombre": "Pere Pons",
                "posicion": "centrocampista",
                "partidos_jugados": 27,
                "partidos_titular": 17,
                "minutos": 1376,
                "goles_marcados": 1,
                "goles_encajados": 0
            },
            {
                "id": "j202425",
                "nombre": "Rioja",
                "posicion": "extremo",
                "partidos_jugados": 37,
                "partidos_titular": 36,
                "minutos": 3127,
                "goles_marcados": 1,
                "goles_encajados": 0
            },
            {
                "id": "j9301",
                "nombre": "Joselu",
                "posicion": "delantero centro",
                "partidos_jugados": 37,
                "partidos_titular": 35,
                "minutos": 3125,
                "goles_marcados": 14,
                "goles_encajados": 0
            },
            {
                "id": "j400405",
                "nombre": "Édgar Méndez",
                "posicion": "extremo",
                "partidos_jugados": 32,
                "partidos_titular": 17,
                "minutos": 1613,
                "goles_marcados": 1,
                "goles_encajados": 0
            },
            {
                "id": "j302291",
                "nombre": "Sivera",
                "posicion": "portero",
                "partidos_jugados": 4,
                "partidos_titular": 3,
                "minutos": 276,
                "goles_marcados": 0,
                "goles_encajados": 4
            },
            {
                "id": "j12421",
                "nombre": "Pina",
                "posicion": "centrocampista",
                "partidos_jugados": 29,
                "partidos_titular": 16,
                "minutos": 1443,
                "goles_marcados": 0,
                "goles_encajados": 0
            },
            {
                "id": "j25059",
                "nombre": "Manu García",
                "posicion": "centrocampista",
                "partidos_jugados": 24,
                "partidos_titular": 10,
                "minutos": 1072,
                "goles_marcados": 0,
                "goles_encajados": 0
            },
            {
                "id": "j300415",
                "nombre": "Ximo",
                "posicion": "lateral derecho",
                "partidos_jugados": 18,
                "partidos_titular": 16,
                "minutos": 1350,
                "goles_marcados": 0,
                "goles_encajados": 0
            },
            {
                "id": "j21442",
                "nombre": "Miguel",
                "posicion": "delantero centro",
                "partidos_jugados": 22,
                "partidos_titular": 10,
                "minutos": 826,
                "goles_marcados": 1,
                "goles_encajados": 0
            },
            {
                "id": "j13161",
                "nombre": "Owono",
                "posicion": "portero",
                "partidos_jugados": 1,
                "partidos_titular": 1,
                "minutos": 90,
                "goles_marcados": 0,
                "goles_encajados": 1
            },
            {
                "id": "j20018",
                "nombre": "Escalante",
                "posicion": "centrocampista",
                "partidos_jugados": 17,
                "partidos_titular": 15,
                "minutos": 1307,
                "goles_marcados": 5,
                "goles_encajados": 0
            },
            {
                "id": "j29650",
                "nombre": "Pellistri",
                "posicion": "extremo",
                "partidos_jugados": 21,
                "partidos_titular": 6,
                "minutos": 663,
                "goles_marcados": 0,
                "goles_encajados": 0
            },
            {
                "id": "j28633",
                "nombre": "Tenaglia",
                "posicion": "lateral derecho",
                "partidos_jugados": 14,
                "partidos_titular": 12,
                "minutos": 1073,
                "goles_marcados": 0,
                "goles_encajados": 0
            },
            {
                "id": "j301766",
                "nombre": "Jason",
                "posicion": "centrocampista",
                "partidos_jugados": 14,
                "partidos_titular": 10,
                "minutos": 683,
                "goles_marcados": 0,
                "goles_encajados": 0
            },
            {
                "id": "j25157",
                "nombre": "Miazga",
                "posicion": "central",
                "partidos_jugados": 11,
                "partidos_titular": 9,
                "minutos": 831,
                "goles_marcados": 0,
                "goles_encajados": 0
            },
            {
                "id": "j301810",
                "nombre": "Sylla",
                "posicion": "delantero centro",
                "partidos_jugados": 13,
                "partidos_titular": 4,
                "minutos": 390,
                "goles_marcados": 0,
                "goles_encajados": 0
            },
            {
                "id": "j26449",
                "nombre": "Javi López",
                "posicion": "lateral izquierdo",
                "partidos_jugados": 9,
                "partidos_titular": 4,
                "minutos": 458,
                "goles_marcados": 0,
                "goles_encajados": 0
            },
            {
                "id": "j91034",
                "nombre": "Guidetti",
                "posicion": "extremo",
                "partidos_jugados": 10,
                "partidos_titular": 2,
                "minutos": 274,
                "goles_marcados": 0,
                "goles_encajados": 0
            },
            {
                "id": "j24250",
                "nombre": "Manu Vallejo",
                "posicion": "extremo",
                "partidos_jugados": 11,
                "partidos_titular": 2,
                "minutos": 364,
                "goles_marcados": 1,
                "goles_encajados": 0
            },
            {
                "id": "j20955",
                "nombre": "Iván Martín",
                "posicion": "centrocampista",
                "partidos_jugados": 6,
                "partidos_titular": 2,
                "minutos": 165,
                "goles_marcados": 0,
                "goles_encajados": 0
            },
            {
                "id": "j24450",
                "nombre": "Tachi",
                "posicion": "central",
                "partidos_jugados": 5,
                "partidos_titular": 2,
                "minutos": 237,
                "goles_marcados": 0,
                "goles_encajados": 0
            },
            {
                "id": "j202089",
                "nombre": "Saúl",
                "posicion": "lateral izquierdo",
                "partidos_jugados": 1,
                "partidos_titular": 0,
                "minutos": 3,
                "goles_marcados": 0,
                "goles_encajados": 0
            },
            {
                "id": "j304038",
                "nombre": "Tenas",
                "posicion": "delantero centro",
                "partidos_jugados": 3,
                "partidos_titular": 0,
                "minutos": 51,
                "goles_marcados": 0,
                "goles_encajados": 0
            },
            {
                "id": "j40342",
                "nombre": "Mendes",
                "posicion": "centrocampista",
                "partidos_jugados": 1,
                "partidos_titular": 0,
                "minutos": 8,
                "goles_marcados": 0,
                "goles_encajados": 0
            },
            {
                "id": "j26397",
                "nombre": "Țîrlea",
                "posicion": "lateral derecho",
                "partidos_jugados": 1,
                "partidos_titular": 0,
                "minutos": 14,
                "goles_marcados": 0,
                "goles_encajados": 0
            },
            {
                "id": "j27824",
                "nombre": "Ropero",
                "posicion": "extremo",
                "partidos_jugados": 1,
                "partidos_titular": 0,
                "minutos": 11,
                "goles_marcados": 0,
                "goles_encajados": 0
            }
        ],
        "Copa del Rey (España)": [
            {
                "id": "j13748",
                "nombre": "Lejeune",
                "posicion": "central",
                "partidos_jugados": 1,
                "partidos_titular": 1,
                "minutos": 90,
                "goles_marcados": 0,
                "goles_encajados": 0
            },
            {
                "id": "j28156",
                "nombre": "Toni Moya",
                "posicion": "centrocampista",
                "partidos_jugados": 2,
                "partidos_titular": 1,
                "minutos": 119,
                "goles_marcados": 0,
                "goles_encajados": 0
            },
            {
                "id": "j16310",
                "nombre": "Pere Pons",
                "posicion": "centrocampista",
                "partidos_jugados": 1,
                "partidos_titular": 1,
                "minutos": 58,
                "goles_marcados": 0,
                "goles_encajados": 0
            },
            {
                "id": "j202425",
                "nombre": "Rioja",
                "posicion": "extremo",
                "partidos_jugados": 2,
                "partidos_titular": 0,
                "minutos": 73,
                "goles_marcados": 1,
                "goles_encajados": 0
            },
            {
                "id": "j9301",
                "nombre": "Joselu",
                "posicion": "delantero centro",
                "partidos_jugados": 1,
                "partidos_titular": 0,
                "minutos": 32,
                "goles_marcados": 0,
                "goles_encajados": 0
            },
            {
                "id": "j400405",
                "nombre": "Édgar Méndez",
                "posicion": "extremo",
                "partidos_jugados": 1,
                "partidos_titular": 1,
                "minutos": 46,
                "goles_marcados": 0,
                "goles_encajados": 0
            },
            {
                "id": "j302291",
                "nombre": "Sivera",
                "posicion": "portero",
                "partidos_jugados": 2,
                "partidos_titular": 2,
                "minutos": 180,
                "goles_marcados": 0,
                "goles_encajados": 2
            },
            {
                "id": "j25059",
                "nombre": "Manu García",
                "posicion": "centrocampista",
                "partidos_jugados": 2,
                "partidos_titular": 1,
                "minutos": 134,
                "goles_marcados": 0,
                "goles_encajados": 0
            },
            {
                "id": "j21442",
                "nombre": "Miguel",
                "posicion": "delantero centro",
                "partidos_jugados": 2,
                "partidos_titular": 1,
                "minutos": 56,
                "goles_marcados": 0,
                "goles_encajados": 0
            },
            {
                "id": "j29650",
                "nombre": "Pellistri",
                "posicion": "extremo",
                "partidos_jugados": 2,
                "partidos_titular": 0,
                "minutos": 88,
                "goles_marcados": 0,
                "goles_encajados": 0
            },
            {
                "id": "j25157",
                "nombre": "Miazga",
                "posicion": "central",
                "partidos_jugados": 1,
                "partidos_titular": 1,
                "minutos": 90,
                "goles_marcados": 0,
                "goles_encajados": 0
            },
            {
                "id": "j301810",
                "nombre": "Sylla",
                "posicion": "delantero centro",
                "partidos_jugados": 2,
                "partidos_titular": 2,
                "minutos": 180,
                "goles_marcados": 2,
                "goles_encajados": 0
            },
            {
                "id": "j26449",
                "nombre": "Javi López",
                "posicion": "lateral izquierdo",
                "partidos_jugados": 2,
                "partidos_titular": 2,
                "minutos": 136,
                "goles_marcados": 0,
                "goles_encajados": 0
            },
            {
                "id": "j91034",
                "nombre": "Guidetti",
                "posicion": "extremo",
                "partidos_jugados": 2,
                "partidos_titular": 2,
                "minutos": 129,
                "goles_marcados": 1,
                "goles_encajados": 0
            },
            {
                "id": "j20955",
                "nombre": "Iván Martín",
                "posicion": "centrocampista",
                "partidos_jugados": 2,
                "partidos_titular": 2,
                "minutos": 107,
                "goles_marcados": 0,
                "goles_encajados": 0
            },
            {
                "id": "j24450",
                "nombre": "Tachi",
                "posicion": "central",
                "partidos_jugados": 2,
                "partidos_titular": 2,
                "minutos": 180,
                "goles_marcados": 0,
                "goles_encajados": 0
            },
            {
                "id": "j202089",
                "nombre": "Saúl",
                "posicion": "lateral izquierdo",
                "partidos_jugados": 1,
                "partidos_titular": 1,
                "minutos": 90,
                "goles_marcados": 0,
                "goles_encajados": 0
            },
            {
                "id": "j20671",
                "nombre": "Abqar",
                "posicion": "central",
                "partidos_jugados": 1,
                "partidos_titular": 0,
                "minutos": 44,
                "goles_marcados": 0,
                "goles_encajados": 0
            },
            {
                "id": "j40342",
                "nombre": "Mendes",
                "posicion": "centrocampista",
                "partidos_jugados": 1,
                "partidos_titular": 0,
                "minutos": 7,
                "goles_marcados": 0,
                "goles_encajados": 0
            },
            {
                "id": "j26397",
                "nombre": "Țîrlea",
                "posicion": "lateral derecho",
                "partidos_jugados": 1,
                "partidos_titular": 1,
                "minutos": 80,
                "goles_marcados": 0,
                "goles_encajados": 0
            },
            {
                "id": "j26445",
                "nombre": "Balboa",
                "posicion": "centrocampista",
                "partidos_jugados": 1,
                "partidos_titular": 1,
                "minutos": 61,
                "goles_marcados": 0,
                "goles_encajados": 0
            }
        ]
    }
}